setup.py
awscodedeploy/__init__.py
awscodedeploy/deploy.py
awscodedeploy/main.py
awscodedeploy/revision.py
awscodedeploy/wait.py
awscodedeploy.egg-info/PKG-INFO
awscodedeploy.egg-info/SOURCES.txt
awscodedeploy.egg-info/dependency_links.txt
awscodedeploy.egg-info/entry_points.txt
awscodedeploy.egg-info/requires.txt
awscodedeploy.egg-info/top_level.txt