Metadata-Version: 1.0
Name: awscodedeploy
Version: 1.2
Summary: CLI for Code Deploy supporting docker-compose
Home-page: http://locationlabs.com
Author: Location Labs
Author-email: info@locationlabs.com
License: UNKNOWN
Platform: UNKNOWN
